robogrid
