Metadata-Version: 1.1
Name: robogrid
Version: 0.5.2
Summary: A robot simulator for rectangular grids and mazes
Home-page: https://github.com/NotBobTheBuilder/robogrid
Author: Jack Wearden
Author-email: jack@jackwearden.co.uk
License: MIT
Keywords: beginner robot grid maze
Platform: UNKNOWN
Classifier: Development Status :: 3 - Alpha
Classifier: Intended Audience :: Developers
Classifier: Intended Audience :: Other Audience
Classifier: License :: OSI Approved :: MIT License
Classifier: Programming Language :: Python :: 2
Classifier: Programming Language :: Python :: 2.6
Classifier: Programming Language :: Python :: 2.7
Classifier: Programming Language :: Python :: 3
Classifier: Programming Language :: Python :: 3.1
Classifier: Programming Language :: Python :: 3.2
Classifier: Programming Language :: Python :: 3.3
